{"component_layers.md":"1b88e508","advanced_plugin.md":"b71cd634","en_advanced_plugin.md":"db33d004","component_contextmenu.md":"fd4c8f42","advanced_class.md":"e446539f","component_controls.md":"5efc46cb","advanced_built-in.md":"2ab1addc","advanced_property.md":"cb0d16e0","advanced_global.md":"7dd7211c","component_setting.md":"b02da861","en_component_contextmenu.md":"dac57cfb","en_component_layers.md":"446fcd07","en_component_setting.md":"f8787f3a","en_advanced_event.md":"6b9d4f68","en_library_dash.md":"d2caad85","en_advanced_built-in.md":"3d9da76b","en_library_flv.md":"7a295dcf","en_index.md":"52c017d9","advanced_event.md":"d7901aca","en_plugin_ads.md":"fef2c55d","en_plugin_control-ui.md":"7d8f6ab6","en_component_controls.md":"c066e6b8","en_advanced_class.md":"a47f0b69","en_library_hls.md":"adcf9c67","en_plugin_dash-quality.md":"6f3533c5","en_advanced_global.md":"15418f1d","en_plugin_hls-quality.md":"7d0ed9c8","en_advanced_property.md":"15b8758c","en_plugin_iframe.md":"c5285e82","en_start_i18n.md":"289526b8","library_flv.md":"a74cc017","library_dash.md":"6145d438","library_hls.md":"29fb7b0e","plugin_ads.md":"245d8c0c","plugin_control-ui.md":"6137df04","plugin_hls-quality.md":"bdc89da6","index.md":"a9f43adc","plugin_dash-quality.md":"4cb78e94","start_i18n.md":"10f50a88","plugin_iframe.md":"82b9b872","en_start_option.md":"096c4d13","plugin_danmuku.md":"f7f4ca03","start_option.md":"81dcd571"}
