{"advanced_built-in.md":"Bldexs_p","advanced_class.md":"DW6X4M9D","advanced_event.md":"C2SzJaTy","advanced_global.md":"7F5EmAmp","advanced_plugin.md":"CcxzffzL","advanced_property.md":"WK_hnSQQ","component_contextmenu.md":"DIxhUvsb","component_controls.md":"DPBlHcNT","component_layers.md":"C_s3YQku","component_setting.md":"nZxvBxGI","en_advanced_built-in.md":"Bx4WnMfL","en_advanced_class.md":"Bu2Ctkut","en_advanced_event.md":"D5hRp_mX","en_advanced_global.md":"CHcnY62M","en_advanced_plugin.md":"CQZZIC-J","en_advanced_property.md":"DBbQrs1R","en_component_contextmenu.md":"D4Z-x5sp","en_component_controls.md":"Bres92St","en_component_layers.md":"D7Jveq87","en_component_setting.md":"CfRyuJXh","en_index.md":"DtcpTTeZ","en_start_i18n.md":"HQ_N7w9M","en_start_option.md":"RIH5lKBb","index.md":"BkjT_x0c","plugin_danmuku.md":"ZE_oW1Mj","start_i18n.md":"4BkMaXCg","start_option.md":"Cx_IMYGD"}
